docassemble.MassAppealsCourt-0.2.3-py3.10-nspkg.pth
docassemble/MassAppealsCourt/__init__.py
docassemble/MassAppealsCourt/ma_appeals_specific_logic.py
docassemble/MassAppealsCourt/data/questions/appeals-basic-questions.yml
docassemble/MassAppealsCourt/data/questions/efiling.yml
docassemble/MassAppealsCourt/data/sources/README.md
docassemble/MassAppealsCourt/data/static/README.md
docassemble/MassAppealsCourt/data/templates/README.md
docassemble/MassAppealsCourt/data/templates/appeals_cover_sheet.docx
docassemble.MassAppealsCourt-0.2.3.dist-info/LICENSE
docassemble.MassAppealsCourt-0.2.3.dist-info/METADATA
docassemble.MassAppealsCourt-0.2.3.dist-info/WHEEL
docassemble.MassAppealsCourt-0.2.3.dist-info/namespace_packages.txt
docassemble.MassAppealsCourt-0.2.3.dist-info/top_level.txt
docassemble.MassAppealsCourt-0.2.3.dist-info/RECORD
