Metadata-Version: 2.1
Name: docassemble.MassAppealsCourt
Version: 0.2.3
Summary: A docassemble extension for working with the Massachusetts Appeals Court
Home-page: https://corutformsonline.org
Author: Quinten Steenhuis
Author-email: massaccess@suffolk.edu
License: The MIT License (MIT)
License-File: LICENSE
Requires-Dist: docassemble.AssemblyLine
